qth_notify/__init__.py
qth_notify-0.0.3.dist-info/LICENSE
qth_notify-0.0.3.dist-info/METADATA
qth_notify-0.0.3.dist-info/WHEEL
qth_notify-0.0.3.dist-info/entry_points.txt
qth_notify-0.0.3.dist-info/top_level.txt
qth_notify-0.0.3.dist-info/RECORD
