Metadata-Version: 2.1
Name: qth-notify
Version: 0.0.3
License: GNU GENERAL PUBLIC LICENSE
Project-URL: homepage, https://github.com/mossblaser/qth_notify
License-File: LICENSE
Requires-Dist: qth
Requires-Dist: desktop-notify
Requires-Dist: dbus-next
